gremllm/__init__.py
gremllm/core.py
gremllm-0.2.0.dist-info/licenses/LICENSE
gremllm-0.2.0.dist-info/METADATA
gremllm-0.2.0.dist-info/WHEEL
gremllm-0.2.0.dist-info/top_level.txt
gremllm-0.2.0.dist-info/RECORD
